typhoon/__init__.py
typhoon/version.py
typhoon/allure_commons/__init__.py
typhoon/allure_commons/cli_logger.cpython-311-x86_64-linux-gnu.so
typhoon/allure_realtime/__init__.py
typhoon/allure_realtime/listener.cpython-311-x86_64-linux-gnu.so
typhoon/allure_realtime/plugin.cpython-311-x86_64-linux-gnu.so
typhoon/allure_step/__init__.py
typhoon/env_api/__init__.py
typhoon/env_api/constants.cpython-311-x86_64-linux-gnu.so
typhoon/env_api/exceptions.cpython-311-x86_64-linux-gnu.so
typhoon/env_api/stub.cpython-311-x86_64-linux-gnu.so
typhoon/logger/__init__.py
typhoon/logger/const.cpython-311-x86_64-linux-gnu.so
typhoon/messaging/__init__.py
typhoon/messaging/msg_types.cpython-311-x86_64-linux-gnu.so
typhoon/messaging/proxy.cpython-311-x86_64-linux-gnu.so
typhoon/path/__init__.py
typhoon/path/standard_paths.cpython-311-x86_64-linux-gnu.so
typhoon/pytest_typhoon/__init__.py
typhoon/pytest_typhoon/decorators.cpython-311-x86_64-linux-gnu.so
typhoon/pytest_typhoon/plugin.cpython-311-x86_64-linux-gnu.so
typhoon/pytest_typhoon/typhoon_test_ide.cpython-311-x86_64-linux-gnu.so
typhoon/test/__init__.py
typhoon/test/ranges.cpython-311-x86_64-linux-gnu.so
typhoon/test/IEC61000/__init__.py
typhoon/test/IEC61000/flickmeter.cpython-311-x86_64-linux-gnu.so
typhoon/test/IEC61000/impl.cpython-311-x86_64-linux-gnu.so
typhoon/test/IEC61000/power_quantities.cpython-311-x86_64-linux-gnu.so
typhoon/test/IEC61000/power_quantities_3ph.cpython-311-x86_64-linux-gnu.so
typhoon/test/IEC61000/utils.cpython-311-x86_64-linux-gnu.so
typhoon/test/capture/__init__.py
typhoon/test/capture/impl.cpython-311-x86_64-linux-gnu.so
typhoon/test/harmonic/__init__.py
typhoon/test/harmonic/impl.cpython-311-x86_64-linux-gnu.so
typhoon/test/power/__init__.py
typhoon/test/power/impl.cpython-311-x86_64-linux-gnu.so
typhoon/test/reporting/__init__.py
typhoon/test/reporting/figures/__init__.py
typhoon/test/reporting/figures/impl.cpython-311-x86_64-linux-gnu.so
typhoontest-1.35.1.dist-info/METADATA
typhoontest-1.35.1.dist-info/WHEEL
typhoontest-1.35.1.dist-info/entry_points.txt
typhoontest-1.35.1.dist-info/top_level.txt
typhoontest-1.35.1.dist-info/RECORD
